otto/__init__.py
otto/cli.py
otto/utils.py
otto/files/.dockerignore
otto/files/.gitignore
otto/files/Dockerfile
otto/files/MLproject
otto/files/README.md
otto/files/build_image.sh
otto/files/model.py
otto/files/settings.py
otto/files/train.py
otto/utils/__init__.py
otto/utils/files.py
otto/utils/mlflow.py
otto_ml-0.1.31.dist-info/LICENSE
otto_ml-0.1.31.dist-info/METADATA
otto_ml-0.1.31.dist-info/WHEEL
otto_ml-0.1.31.dist-info/entry_points.txt
otto_ml-0.1.31.dist-info/top_level.txt
otto_ml-0.1.31.dist-info/RECORD
