Metadata-Version: 2.1
Name: otto-ml
Version: 0.1.31
Summary: Otto is a simple Boilerplate for Machine Learning projects integrated with MLflow tools
Home-page: https://github.com/carlos-rodrigo/otto-ml
Author: Carlos Rodrigo
Author-email: hi@carlosrodrigo.me
License: UNKNOWN
Platform: UNKNOWN
Classifier: Programming Language :: Python :: 3
Classifier: License :: OSI Approved :: MIT License
Classifier: Operating System :: OS Independent
Requires-Python: >=3.5
Requires-Dist: click (>=7.0)
Requires-Dist: numpy
Requires-Dist: pandas
Requires-Dist: mlflow
Provides-Extra: extras
Requires-Dist: boto3 (>=1.7.12) ; extra == 'extras'
Requires-Dist: scikit-learn (==0.20) ; (python_version < "3.5") and extra == 'extras'
Requires-Dist: scikit-learn ; (python_version >= "3.5") and extra == 'extras'
